.pycheckrc
CHANGES
INSTALL
LICENSE
Makefile
README
TODO
VERSION
ez_setup.py
setup.cfg
setup.py
Salamoia.egg-info/PKG-INFO
Salamoia.egg-info/SOURCES.txt
Salamoia.egg-info/dependency_links.txt
Salamoia.egg-info/entry_points.txt
Salamoia.egg-info/requires.txt
Salamoia.egg-info/top_level.txt
bin/exprem
bin/kill-nacl
bin/macina
bin/nacl
bin/nacl.tmpl
bin/profstat
bin/salamoia
bin/salamoia-console
bin/src-doctest.sh
bin/test
bin/testSrv
bundles/Makefile
bundles/common.mk
bundles/authmanager/Makefile
bundles/authmanager/VERSION
bundles/authmanager/setup.py
bundles/authmanager/authmanager/__init__.py
bundles/authmanager/authmanager/authmanager.py
bundles/authmanager/authmanager/service.xml
bundles/autistici/Makefile
bundles/autistici/VERSION
bundles/autistici/setup.py
bundles/autistici/autistici/__init__.py
bundles/autistici/autistici/commonUser.xml
bundles/autistici/autistici/investiciObject.xml
bundles/autistici/autistici/posixAccount.xml
bundles/autistici/autistici/schema.xml
bundles/autistici/autistici/service.xml
bundles/autistici/autistici/ldap/__init__.py
bundles/autistici/autistici/ldap/base-schema.xml
bundles/autistici/autistici/ldap/domains.xml
bundles/autistici/autistici/ldap/organizational.xml
bundles/dma/Makefile
bundles/dma/VERSION
bundles/dma/setup.py
bundles/dma/dma/__init__.py
bundles/dma/dma/commonUser.xml
bundles/dma/dma/posixAccount.xml
bundles/dma/dma/schema.xml
bundles/dma/dma/service.xml
bundles/dma/dma/ldap/__init__.py
bundles/dma/dma/ldap/base-schema.xml
bundles/dma/dma/ldap/dhcpService.xml
bundles/dma/dma/ldap/ipnetwork.xml
bundles/dma/dma/ldap/organizational.xml
bundles/local-schema/Makefile
bundles/local-schema/VERSION
bundles/local-schema/setup.py
bundles/local-schema/local/__init__.py
bundles/local-schema/local/schema.xml
bundles/local-schema/local/service.xml
bundles/schema/Makefile
bundles/schema/README
bundles/schema/VERSION
bundles/schema/setup.py
bundles/schema/hostello/__init__.py
bundles/schema/hostello/auth.py
bundles/schema/hostello/schema.xml
bundles/schema/hostello/service.xml
bundles/schema/hostello/ldap/__init__.py
bundles/schema/hostello/ldap/base-schema.xml
bundles/schema/hostello/ldap/organizational.xml
