Metadata-Version: 1.0
Name: Salamoia
Version: 1.1.6
Summary: Ldap based framework for distributed administration
Home-page: http://salamoia.org
Author: Marko Mikulicic, Paolo De Rosa
Author-email: marko@autistici.org, phasa@autistici.org
License: GPL
Platform: UNKNOWN
Classifier: Operating System :: POSIX
Classifier: Intended Audience :: System Administrators
Classifier: Intended Audience :: Developers
Classifier: Environment :: Console
Classifier: Environment :: Web Environment
